kcleaner.py
kcleaner-0.3.3.dist-info/LICENSE
kcleaner-0.3.3.dist-info/METADATA
kcleaner-0.3.3.dist-info/WHEEL
kcleaner-0.3.3.dist-info/entry_points.txt
kcleaner-0.3.3.dist-info/top_level.txt
kcleaner-0.3.3.dist-info/RECORD
